LICENSE
README.md
setup.py
src/extracTR.egg-info/PKG-INFO
src/extracTR.egg-info/SOURCES.txt
src/extracTR.egg-info/dependency_links.txt
src/extracTR.egg-info/entry_points.txt
src/extracTR.egg-info/requires.txt
src/extracTR.egg-info/top_level.txt
src/extractr/__init__.py
src/extractr/benchmark.py
src/extractr/extractr.py
src/extractr.egg-info/PKG-INFO
src/extractr.egg-info/SOURCES.txt
src/extractr.egg-info/dependency_links.txt
src/extractr.egg-info/entry_points.txt
src/extractr.egg-info/requires.txt
src/extractr.egg-info/top_level.txt
src/extractr/core_functions/__init__.py
src/extractr/core_functions/evaluation.py
src/extractr/core_functions/helpers.py
src/extractr/core_functions/index_tools.py
src/extractr/core_functions/sdat_tools.py
src/extractr/core_functions/tr_finder.py
src/extractr/core_functions/tr_finder_var.py