Metadata-Version: 2.1
Name: extracTR
Version: 0.2.17
Summary: Extract and analyze satellite DNA from raw sequences.
Home-page: https://github.com/aglabx/extracTR
Author: Aleksey Komissarov
Author-email: ad3002@gmail.com
License: BSD
Classifier: Development Status :: 4 - Beta
Classifier: Environment :: Console
Classifier: Intended Audience :: Science/Research
Classifier: License :: OSI Approved :: BSD License
Classifier: Operating System :: OS Independent
Classifier: Programming Language :: Python
Classifier: Topic :: Scientific/Engineering :: Bio-Informatics
Requires-Python: >=3.6
License-File: LICENSE
Requires-Dist: tqdm
Requires-Dist: intervaltree
Requires-Dist: aindex2
